AUTHORS.rst
CONTRIBUTING.rst
LICENSE
MANIFEST.in
README.rst
setup.cfg
setup.py
docs/Makefile
docs/authors.rst
docs/conf.py
docs/contributing.rst
docs/index.rst
docs/make.bat
docs/readme.rst
docs/_templates/module.rst
docs/_templates/package.rst
src/doi/__init__.py
src/doi.egg-info/PKG-INFO
src/doi.egg-info/SOURCES.txt
src/doi.egg-info/dependency_links.txt
src/doi.egg-info/not-zip-safe
src/doi.egg-info/requires.txt
src/doi.egg-info/top_level.txt
src/python_doi.egg-info/PKG-INFO
src/python_doi.egg-info/SOURCES.txt
src/python_doi.egg-info/dependency_links.txt
src/python_doi.egg-info/not-zip-safe
src/python_doi.egg-info/requires.txt
src/python_doi.egg-info/top_level.txt
tests/test_doi.py
tests/resources/doc.pdf