Metadata-Version: 2.1
Name: python-doi
Version: 0.1.0
Summary: Python package to work with Document Object Identifier (doi)
Home-page: https://github.com/alejandrogallo/doi
Author: Alejandro Gallo
Author-email: aamsgallo@gmail.com
License: GNU General Public License v3
Keywords: doi
Platform: UNKNOWN
Classifier: Development Status :: 2 - Pre-Alpha
Classifier: Intended Audience :: Developers
Classifier: License :: OSI Approved :: GNU General Public License v3 (GPLv3)
Classifier: Natural Language :: English
Classifier: Programming Language :: Python :: 3.4
Classifier: Programming Language :: Python :: 3.5
Classifier: Programming Language :: Python :: 3.6
Provides-Extra: dev
